Workbook

Sheet Supuestos
A1: Cloud Socks · Supuestos
A2: Editá solo las celdas amarillas con texto azul. Todo lo demás se recalcula solo.
A4: Concepto | B4: Valor | C4: Nota
A5: Costo por par (ARS) | B5: 2300 | C5: Dato del usuario.
A6: Envío por pedido (ARS) | B6: 10500 | C6: Dato del usuario. Supuesto: lo paga la marca, 1 envío por pedido.
A7: Packaging por pedido (ARS) | B7: 500 | C7: Dato del usuario.
A8: Tarjeta por pedido (ARS) | B8: 200 | C8: Estimado. Reemplazar por el costo real.
A9: Comisión Mercado Pago (sin IVA) | B9: 0.0629 | C9: Acreditación inmediata. Verificar en el panel de MP, cambia seguido.
A10: IVA sobre comisión MP | B10: 0.21 | C10: IVA 21% sobre la comisión.
A11: Comisión Shopify por venta | B11: 0.02 | C11: Plan Basic sin Shopify Payments (no disponible en Argentina).
A12: Costo extra 3 cuotas sin interés | B12: 0.1 | C12: Aproximado. Verificar la tasa exacta en el panel de MP.
A13: Cuota mensual monotributo (ARS) | B13: 60000 | C13: Ejemplo. Reemplazar por la cuota real de tu categoría (ARCA).
A14: Pedidos estimados por mes | B14: 100 | C14: Para repartir el monotributo por pedido.
A15: ROAS objetivo | B15: 2.5 | C15: Retorno de publicidad que querés lograr.
A16: Comisión MP total (con IVA) | B16: =B9*(1+B10)
A17: Monotributo por pedido (ARS) | B17: =IFERROR(B13/B14,0)

Sheet Costeo por pack
A1: Cloud Socks · Costeo por pack: CM1, CM2, CM3, CPA y ROAS de break-even
A2: CM1 = precio − producto · CM2 = CM1 − costos variables de venta · CM3 = CM2 − publicidad (CPA a ROAS objetivo). Editá solo lo amarillo.
A4: Pack | B4: Pares | C4: Precio venta | D4: 3 cuotas s/int. (Sí/No) | E4: Producto | F4: CM1 | G4: CM1 % | H4: Envío | I4: Packaging + tarjeta | J4: Mercado Pago | K4: Shopify | L4: Cuotas s/int. | M4: CM2 | N4: CM2 % | O4: Monotributo x pedido | P4: CPA break-even | Q4: ROAS break-even | R4: CPA a ROAS objetivo | S4: CM3 | T4: CM3 % | U4: Resultado neto x pedido | V4: Precio por par
A5: 1 par | B5: 1 | C5: 33900 | D5: No | E5: =B5*Supuestos!$B$5 | F5: =C5-E5 | G5: =IFERROR(F5/C5,0) | H5: =Supuestos!$B$6 | I5: =Supuestos!$B$7+Supuestos!$B$8 | J5: =C5*Supuestos!$B$16 | K5: =C5*Supuestos!$B$11 | L5: =IF(D5="Sí",C5*Supuestos!$B$12,0) | M5: =F5-SUM(H5:L5) | N5: =IFERROR(M5/C5,0) | O5: =Supuestos!$B$17 | P5: =M5-O5 | Q5: =IFERROR(C5/P5,0) | R5: =IFERROR(C5/Supuestos!$B$15,0) | S5: =M5-R5 | T5: =IFERROR(S5/C5,0) | U5: =S5-O5 | V5: =IFERROR(C5/B5,0)
A6: Llevá 3, pagá 2 | B6: 3 | C6: 46900 | D6: No | E6: =B6*Supuestos!$B$5 | F6: =C6-E6 | G6: =IFERROR(F6/C6,0) | H6: =Supuestos!$B$6 | I6: =Supuestos!$B$7+Supuestos!$B$8 | J6: =C6*Supuestos!$B$16 | K6: =C6*Supuestos!$B$11 | L6: =IF(D6="Sí",C6*Supuestos!$B$12,0) | M6: =F6-SUM(H6:L6) | N6: =IFERROR(M6/C6,0) | O6: =Supuestos!$B$17 | P6: =M6-O6 | Q6: =IFERROR(C6/P6,0) | R6: =IFERROR(C6/Supuestos!$B$15,0) | S6: =M6-R6 | T6: =IFERROR(S6/C6,0) | U6: =S6-O6 | V6: =IFERROR(C6/B6,0)
A7: Llevá 6, pagá 3 | B7: 6 | C7: 69900 | D7: No | E7: =B7*Supuestos!$B$5 | F7: =C7-E7 | G7: =IFERROR(F7/C7,0) | H7: =Supuestos!$B$6 | I7: =Supuestos!$B$7+Supuestos!$B$8 | J7: =C7*Supuestos!$B$16 | K7: =C7*Supuestos!$B$11 | L7: =IF(D7="Sí",C7*Supuestos!$B$12,0) | M7: =F7-SUM(H7:L7) | N7: =IFERROR(M7/C7,0) | O7: =Supuestos!$B$17 | P7: =M7-O7 | Q7: =IFERROR(C7/P7,0) | R7: =IFERROR(C7/Supuestos!$B$15,0) | S7: =M7-R7 | T7: =IFERROR(S7/C7,0) | U7: =S7-O7 | V7: =IFERROR(C7/B7,0)
A8: Llevá 12, pagá 6 | B8: 12 | C8: 139800 | D8: No | E8: =B8*Supuestos!$B$5 | F8: =C8-E8 | G8: =IFERROR(F8/C8,0) | H8: =Supuestos!$B$6 | I8: =Supuestos!$B$7+Supuestos!$B$8 | J8: =C8*Supuestos!$B$16 | K8: =C8*Supuestos!$B$11 | L8: =IF(D8="Sí",C8*Supuestos!$B$12,0) | M8: =F8-SUM(H8:L8) | N8: =IFERROR(M8/C8,0) | O8: =Supuestos!$B$17 | P8: =M8-O8 | Q8: =IFERROR(C8/P8,0) | R8: =IFERROR(C8/Supuestos!$B$15,0) | S8: =M8-R8 | T8: =IFERROR(S8/C8,0) | U8: =S8-O8 | V8: =IFERROR(C8/B8,0)
A10: No incluye retenciones de Ingresos Brutos ni IVA/Ganancias si pasás a Responsable Inscripto.

Sheet Mix de ventas
A1: Cloud Socks · CM1, CM2, CM3, CPA y ROAS según el mix de ventas
A2: Poné en amarillo qué % de los pedidos es cada pack (tiene que sumar 100%). Ejemplo: 15/25/50/10.
A4: Pack | B4: % de pedidos | C4: Precio | D4: CM1 | E4: CM2 | F4: CM3
A5: ='Costeo por pack'!A5 | B5: 0.15 | C5: ='Costeo por pack'!C5 | D5: ='Costeo por pack'!F5 | E5: ='Costeo por pack'!M5 | F5: ='Costeo por pack'!S5
A6: ='Costeo por pack'!A6 | B6: 0.25 | C6: ='Costeo por pack'!C6 | D6: ='Costeo por pack'!F6 | E6: ='Costeo por pack'!M6 | F6: ='Costeo por pack'!S6
A7: ='Costeo por pack'!A7 | B7: 0.5 | C7: ='Costeo por pack'!C7 | D7: ='Costeo por pack'!F7 | E7: ='Costeo por pack'!M7 | F7: ='Costeo por pack'!S7
A8: ='Costeo por pack'!A8 | B8: 0.1 | C8: ='Costeo por pack'!C8 | D8: ='Costeo por pack'!F8 | E8: ='Costeo por pack'!M8 | F8: ='Costeo por pack'!S8
A9: Total % | B9: =SUM(B5:B8) | C9: =IF(ROUND(B9,4)=1,"OK","Revisá: no suma 100%")
A11: Resultados del mix
A12: Ticket promedio (AOV) | B12: =SUMPRODUCT(B5:B8,C5:C8)
A13: CM1 promedio | B13: =SUMPRODUCT(B5:B8,D5:D8)
A14: CM1 % | B14: =IFERROR(B13/B12,0)
A15: CM2 promedio | B15: =SUMPRODUCT(B5:B8,E5:E8)
A16: CM2 % | B16: =IFERROR(B15/B12,0)
A17: CPA break-even (mix) | B17: =B15-Supuestos!$B$17
A18: ROAS break-even (mix) | B18: =IFERROR(B12/B17,0)
A19: CPA a ROAS objetivo | B19: =IFERROR(B12/Supuestos!$B$15,0)
A20: CM3 promedio (a ROAS objetivo) | B20: =SUMPRODUCT(B5:B8,F5:F8)
A21: CM3 % | B21: =IFERROR(B20/B12,0)
A22: Resultado neto por pedido | B22: =B20-Supuestos!$B$17
